sbmltoodejax/__init__.py
sbmltoodejax/biomodels_api.py
sbmltoodejax/jaxfuncs.py
sbmltoodejax/modulegeneration.py
sbmltoodejax/parse.py
sbmltoodejax/utils.py
sbmltoodejax-0.4.3.dist-info/LICENSE
sbmltoodejax-0.4.3.dist-info/METADATA
sbmltoodejax-0.4.3.dist-info/WHEEL
sbmltoodejax-0.4.3.dist-info/top_level.txt
sbmltoodejax-0.4.3.dist-info/RECORD
