Metadata-Version: 2.1
Name: sbmltoodejax
Version: 0.4.3
Summary: lightweight library that allows to automatically parse and convert SBML models into python models written end-to-end in JAX
Home-page: https://github.com/flowersteam/sbmltoodejax
Author: Mayalen Etcheverry
Author-email: mayalen.etcheverry@inria.fr
License: MIT
Classifier: Programming Language :: Python :: 3
Classifier: License :: OSI Approved :: MIT License
Classifier: Operating System :: OS Independent
License-File: LICENSE
Requires-Dist: sbmltoodepy
Requires-Dist: jax[cpu]
Requires-Dist: equinox
